edx_release_notes-0.1.2.dist-info/licenses/LICENSE.txt
release_notes/__init__.py
release_notes/admin.py
release_notes/apps.py
release_notes/models.py
release_notes/permissions.py
release_notes/toggles.py
release_notes/urls.py
release_notes/api/__init__.py
release_notes/api/v1/__init__.py
release_notes/api/v1/serializers.py
release_notes/api/v1/urls.py
release_notes/api/v1/views.py
release_notes/migrations/0001_initial.py
release_notes/migrations/__init__.py
release_notes/settings/__init__.py
release_notes/settings/common.py
release_notes/settings/devstack.py
release_notes/settings/production.py
release_notes/templates/release_notes/base.html
edx_release_notes-0.1.2.dist-info/METADATA
edx_release_notes-0.1.2.dist-info/WHEEL
edx_release_notes-0.1.2.dist-info/entry_points.txt
edx_release_notes-0.1.2.dist-info/top_level.txt
edx_release_notes-0.1.2.dist-info/RECORD
